{"data_headers":{"result_code":1},"data":{"category":{"pr_category_id":"1","more_posts":true,"priority_lower_than":"1132","contents":[{"article_id":1134,"priority":1138,"category_name":"News","pr_category_id":"1","caption_type":"none","pr_thumb_type":null,"title_name":"Dragalia Life #217, Now Available!","image_path":"","date":1583733600,"is_new":false,"is_update":false,"update_time":1583404744},{"article_id":1126,"priority":1136,"category_name":"News","pr_category_id":"1","caption_type":"none","pr_thumb_type":null,"title_name":"A Gift of Quality Honey and Blessed Ethon Ashes!","image_path":"","date":1583474400,"is_new":false,"is_update":false,"update_time":1583223906},{"article_id":1120,"priority":1135,"category_name":"News","pr_category_id":"1","caption_type":"none","pr_thumb_type":null,"title_name":"Dragalia Life #216, Now Available!","image_path":"","date":1583474400,"is_new":false,"is_update":false,"update_time":1582801836},{"article_id":1125,"priority":1134,"category_name":"News","pr_category_id":"1","caption_type":"none","pr_thumb_type":null,"title_name":"A Gift of 1,200 Wyrmite!","image_path":"","date":1583388000,"is_new":false,"is_update":false,"update_time":1583223812},{"article_id":1127,"priority":1133,"category_name":"News","pr_category_id":"1","caption_type":"none","pr_thumb_type":null,"title_name":"Regarding Connection Issues in Co-op Quests","image_path":"","date":1583314200,"is_new":false,"is_update":false,"update_time":1583459770},{"article_id":1124,"priority":1132,"category_name":"News","pr_category_id":"1","caption_type":"none","pr_thumb_type":null,"title_name":"Issue Regarding Sword Force Strike Power [Update]","image_path":"","date":1583223900,"is_new":false,"is_update":false,"update_time":1583381614}]},"category_id":"1","new_article_list":[],"update_article_list":[]}}