{"data_headers":{"result_code":1},"data":{"category":{"pr_category_id":"1","more_posts":true,"priority_lower_than":"666","contents":[{"article_id":686,"priority":674,"category_name":"News","pr_category_id":"1","caption_type":"none","pr_thumb_type":"2","title_name":"A Gift of Mana for the Summon Showcase!","image_path":"","date":1566540000,"is_new":false,"is_update":false,"update_time":1569479998},{"article_id":10015,"priority":673,"category_name":"News","pr_category_id":"1","caption_type":"none","pr_thumb_type":null,"title_name":"Event Information","image_path":"https://dragalialost.akamaized.net/attached/information/images/9a6234df7dc6bfda253d9dbc69d7ed19.png","date":1566453600,"is_new":false,"is_update":false,"update_time":1569479748},{"article_id":675,"priority":672,"category_name":"News","pr_category_id":"1","caption_type":"summon","pr_thumb_type":null,"title_name":"Valentine's Hildegarde Is Back! The Next Summon Showcase, Ardent Admirers, Is Now Live!","image_path":"","date":1566453600,"is_new":false,"is_update":false,"update_time":1565940600},{"article_id":685,"priority":671,"category_name":"News","pr_category_id":"1","caption_type":"none","pr_thumb_type":null,"title_name":"My concert's TOTALLY starting! ☆","image_path":"https://dragalialost.akamaized.net/attached/information/images/ebc1c47ccf173078821a57ff7e8808f9.png","date":1566453600,"is_new":false,"is_update":false,"update_time":1569480279},{"article_id":678,"priority":667,"category_name":"News","pr_category_id":"1","caption_type":"none","pr_thumb_type":null,"title_name":"New Prelude Difficulty Added to High Jupiter's Trial!","image_path":"https://dragalialost.akamaized.net/attached/information/images/ce827470f9526e7e707210f885258fef.png","date":1566453600,"is_new":false,"is_update":false,"update_time":1569480969},{"article_id":656,"priority":666,"category_name":"News","pr_category_id":"1","caption_type":"none","pr_thumb_type":null,"title_name":"Wyrmprints Added to the Wyrmprint Treasure Trade Lineup for a Limited Time!","image_path":"","date":1566453600,"is_new":false,"is_update":false,"update_time":1565170187}]},"category_id":"1","new_article_list":[],"update_article_list":[]}}