{"data_headers":{"result_code":1},"data":{"category":{"pr_category_id":"","more_posts":true,"priority_lower_than":"1089","contents":[{"article_id":1082,"priority":1095,"category_name":"伺服器維護","pr_category_id":"3","caption_type":"none","pr_thumb_type":null,"title_name":"2/26 遊戲維護公告【更新】","image_path":"","date":1582092000,"is_new":false,"is_update":false,"update_time":1582696836},{"article_id":1097,"priority":1093,"category_name":"公告","pr_category_id":"1","caption_type":"summon","pr_thumb_type":"6","title_name":"「龍族傳說召喚」舉辦公告","image_path":"","date":1582092000,"is_new":false,"is_update":false,"update_time":1582078676},{"article_id":1070,"priority":1092,"category_name":"公告","pr_category_id":"1","caption_type":"none","pr_thumb_type":null,"title_name":"主線劇情第12章「戰火之霸道」即將公開！","image_path":"https://dragalialost.akamaized.net/attached/information/images/3a3ef4b84abbc16e37166d35019022fa.png","date":1582092000,"is_new":false,"is_update":false,"update_time":1582084377},{"article_id":1079,"priority":1091,"category_name":"公告","pr_category_id":"1","caption_type":"none","pr_thumb_type":null,"title_name":"「輕鬆龍絆」第210話更新","image_path":"","date":1582092000,"is_new":false,"is_update":false,"update_time":1581561157},{"article_id":1081,"priority":1090,"category_name":"版本更新","pr_category_id":"2","caption_type":"none","pr_thumb_type":null,"title_name":"版本更新公告【更新】","image_path":"","date":1582081200,"is_new":false,"is_update":false,"update_time":1582859042},{"article_id":1094,"priority":1089,"category_name":"公告","pr_category_id":"1","caption_type":"none","pr_thumb_type":null,"title_name":"完成「寶龍的挑戰」也無法達成Mission之異常現象公告【更新】","image_path":"","date":1582020000,"is_new":false,"is_update":false,"update_time":1582182003}]},"category_id":"","new_article_list":[],"update_article_list":[]}}