{"data_headers":{"result_code":1},"data":{"category":{"pr_category_id":"1","more_posts":true,"priority_lower_than":"3369","contents":[{"article_id":2879,"priority":3377,"category_name":"News","pr_category_id":"1","caption_type":"none","pr_thumb_type":null,"title_name":"The Raid Event Bonus Is Now Live!","image_path":"https://dragalialost.akamaized.net/attached/information/images/e6af0c94e43bb7a3b61ba486d6fe4a12.png","date":1651212000,"is_new":false,"is_update":false,"update_time":1645507285},{"article_id":3021,"priority":3374,"category_name":"News","pr_category_id":"1","caption_type":"summon","pr_thumb_type":"6","title_name":"A Platinum Showcase Is Now Live! 5★ Gala Dragalia Adventurer Guaranteed!","image_path":"","date":1651039200,"is_new":false,"is_update":false,"update_time":1651030269},{"article_id":10086,"priority":3373,"category_name":"News","pr_category_id":"1","caption_type":"none","pr_thumb_type":"1","title_name":"Event Information","image_path":"https://dragalialost.akamaized.net/attached/information/images/9a6234df7dc6bfda253d9dbc69d7ed19.png","date":1651039200,"is_new":false,"is_update":false,"update_time":1644831705},{"article_id":3019,"priority":3372,"category_name":"News","pr_category_id":"1","caption_type":"summon","pr_thumb_type":"6","title_name":"Gala Dragalia Is Now Live!","image_path":"","date":1651039200,"is_new":false,"is_update":false,"update_time":1648550938},{"article_id":3018,"priority":3370,"category_name":"News","pr_category_id":"1","caption_type":"summon","pr_thumb_type":"6","title_name":"Gala Dragalia Is Coming Soon!","image_path":"","date":1650952800,"is_new":false,"is_update":false,"update_time":1649838884},{"article_id":3020,"priority":3369,"category_name":"News","pr_category_id":"1","caption_type":"summon","pr_thumb_type":"6","title_name":"A Platinum Showcase Is Coming Soon! 5★ Gala Dragalia Adventurer Guaranteed!","image_path":"","date":1650952800,"is_new":false,"is_update":false,"update_time":1648697104}]},"category_id":"1","new_article_list":[],"update_article_list":[]}}