{"data_headers":{"result_code":1},"data":{"category":{"pr_category_id":"1","more_posts":true,"priority_lower_than":"1821","contents":[{"article_id":1810,"priority":1835,"category_name":"お知らせ","pr_category_id":"1","caption_type":"none","pr_thumb_type":null,"title_name":"「ゆるがりあ」第309話掲載","image_path":"","date":1608012000,"is_new":false,"is_update":false,"update_time":1606485875},{"article_id":1830,"priority":1834,"category_name":"お知らせ","pr_category_id":"1","caption_type":"summon","pr_thumb_type":"6","title_name":"「ドラガリアフェス　エクストラ」開催決定！","image_path":"","date":1607925600,"is_new":false,"is_update":false,"update_time":1607569041},{"article_id":1835,"priority":1827,"category_name":"お知らせ","pr_category_id":"1","caption_type":"none","pr_thumb_type":null,"title_name":"「星竜祭ログインボーナス」開催！","image_path":"https://dragalialost.akamaized.net/attached/information/images/fdc6ff5f333f20943cf1d23dc9492a2f.png","date":1607925600,"is_new":false,"is_update":false,"update_time":1607665270},{"article_id":1839,"priority":1826,"category_name":"お知らせ","pr_category_id":"1","caption_type":"none","pr_thumb_type":null,"title_name":"「追いうちダメージ」について","image_path":"","date":1607925600,"is_new":false,"is_update":false,"update_time":1607922809},{"article_id":1838,"priority":1822,"category_name":"お知らせ","pr_category_id":"1","caption_type":"none","pr_thumb_type":null,"title_name":"ラジオのお庭「ご意見ボックス」返答（11/29放送）","image_path":"","date":1607666400,"is_new":false,"is_update":false,"update_time":1607496558},{"article_id":1821,"priority":1821,"category_name":"お知らせ","pr_category_id":"1","caption_type":"none","pr_thumb_type":null,"title_name":"「ナームのわくわく冒険記！」第20話掲載","image_path":"","date":1607666400,"is_new":false,"is_update":false,"update_time":1606991791}]},"category_id":"1","new_article_list":[],"update_article_list":[]}}