{"data_headers":{"result_code":1},"data":{"category":{"pr_category_id":"1","more_posts":true,"priority_lower_than":"2769","contents":[{"article_id":2761,"priority":2777,"category_name":"お知らせ","pr_category_id":"1","caption_type":"none","pr_thumb_type":null,"title_name":"武器スキン「フェイタルアルター」の武器種の不具合について【更新】","image_path":"","date":1641967200,"is_new":false,"is_update":false,"update_time":1643096195},{"article_id":2759,"priority":2776,"category_name":"お知らせ","pr_category_id":"1","caption_type":"none","pr_thumb_type":null,"title_name":"アイテム召喚時にエラーが発生した際、「リトライ」を選択すると追加でアイテム召喚が行われる現象について","image_path":"","date":1641880800,"is_new":false,"is_update":false,"update_time":1641865789},{"article_id":2756,"priority":2775,"category_name":"お知らせ","pr_category_id":"1","caption_type":"none","pr_thumb_type":null,"title_name":"召喚のエラーにて「リトライ」を選択すると、追加で召喚が行われる現象について","image_path":"","date":1641880800,"is_new":false,"is_update":false,"update_time":1641865031},{"article_id":2750,"priority":2771,"category_name":"お知らせ","pr_category_id":"1","caption_type":"none","pr_thumb_type":null,"title_name":"ラジオのお庭「ご意見ボックス」返答（12/26放送）","image_path":"","date":1641535200,"is_new":false,"is_update":false,"update_time":1641445921},{"article_id":2730,"priority":2770,"category_name":"お知らせ","pr_category_id":"1","caption_type":"none","pr_thumb_type":null,"title_name":"「ゆるがりあ」第423話掲載","image_path":"","date":1641535200,"is_new":false,"is_update":false,"update_time":1640323283},{"article_id":2751,"priority":2769,"category_name":"お知らせ","pr_category_id":"1","caption_type":"none","pr_thumb_type":null,"title_name":"一部クエストにおいて、特定の解放条件を満たしていない状態でもプレイすることができてしまう現象について","image_path":"","date":1641448800,"is_new":false,"is_update":false,"update_time":1643096361}]},"category_id":"1","new_article_list":[],"update_article_list":[]}}