{"data_headers":{"result_code":1},"data":{"category":{"pr_category_id":"1","more_posts":true,"priority_lower_than":"307","contents":[{"article_id":268,"priority":317,"category_name":"お知らせ","pr_category_id":"1","caption_type":"none","pr_thumb_type":null,"title_name":"配信国追加記念プレゼント！","image_path":"","date":1551160800,"is_new":false,"is_update":false,"update_time":1551160924},{"article_id":267,"priority":316,"category_name":"お知らせ","pr_category_id":"1","caption_type":"none","pr_thumb_type":null,"title_name":"配信国追加キャンペーン開催中！","image_path":"","date":1551160800,"is_new":false,"is_update":false,"update_time":1551160882},{"article_id":264,"priority":313,"category_name":"お知らせ","pr_category_id":"1","caption_type":"none","pr_thumb_type":null,"title_name":"「ゆるがりあ」第73話掲載","image_path":"","date":1551074400,"is_new":false,"is_update":false,"update_time":1551062158},{"article_id":262,"priority":311,"category_name":"お知らせ","pr_category_id":"1","caption_type":"none","pr_thumb_type":null,"title_name":"ヴォイド討伐戦の「交換所」が表示されない現象について【追記】","image_path":"","date":1550818800,"is_new":false,"is_update":false,"update_time":1550830262},{"article_id":261,"priority":310,"category_name":"お知らせ","pr_category_id":"1","caption_type":"none","pr_thumb_type":null,"title_name":"ヴォイド討伐戦におけるイベントトップページの誤表記について","image_path":"","date":1550818200,"is_new":false,"is_update":false,"update_time":1550835188},{"article_id":260,"priority":307,"category_name":"お知らせ","pr_category_id":"1","caption_type":"none","pr_thumb_type":null,"title_name":"「ヴォイド討伐戦」登場＆期間限定ミッション開催！","image_path":"","date":1550815200,"is_new":false,"is_update":false,"update_time":1553063296}]},"category_id":"1","new_article_list":[],"update_article_list":[]}}