{"data_headers":{"result_code":1},"data":{"category":{"pr_category_id":"4","more_posts":true,"priority_lower_than":"1082","contents":[{"article_id":1087,"priority":1097,"category_name":"活动","pr_category_id":"4","caption_type":"event","pr_thumb_type":null,"title_name":"“虚空之影讨伐战”追加新的虚空之影＆期间限定目标开放！","image_path":"https://dragalialost.akamaized.net/attached/information/images/0fd010dbf13127017550a35ca769fe2f.png","date":1582178400,"is_new":false,"is_update":false,"update_time":1581673868},{"article_id":1085,"priority":1088,"category_name":"活动","pr_category_id":"4","caption_type":"event","pr_thumb_type":null,"title_name":"“暗蚀奇美拉”将在虚空之影讨伐战中登场！","image_path":"https://dragalialost.akamaized.net/attached/information/images/0fd010dbf13127017550a35ca769fe2f.png","date":1582005600,"is_new":false,"is_update":false,"update_time":1581672218},{"article_id":1089,"priority":1087,"category_name":"活动","pr_category_id":"4","caption_type":"none","pr_thumb_type":null,"title_name":"“星魂解放团队战”即将登场！","image_path":"https://dragalialost.akamaized.net/attached/information/images/6e322df872571aec3a4a3449c8c0ff7a.png","date":1581919200,"is_new":false,"is_update":false,"update_time":1581902409},{"article_id":1091,"priority":1085,"category_name":"活动","pr_category_id":"4","caption_type":"event","pr_thumb_type":null,"title_name":"活动“MONSTER HUNTER STRANGELAND”终章追加！","image_path":"https://dragalialost.akamaized.net/attached/information/images/253c39e59a1acdb1111fb32c9b254581.png","date":1581919200,"is_new":false,"is_update":false,"update_time":1581671648},{"article_id":1074,"priority":1083,"category_name":"活动","pr_category_id":"4","caption_type":"event","pr_thumb_type":null,"title_name":"剧情活动【复刻】“情人节·甜美佳肴”新剧情追加！","image_path":"https://dragalialost.akamaized.net/attached/information/images/0e73bcd88781f55edbf698b587707aa2.png","date":1581919200,"is_new":false,"is_update":false,"update_time":1581321809},{"article_id":20000,"priority":1082,"category_name":"活动","pr_category_id":"4","caption_type":"event","pr_thumb_type":null,"title_name":"宝龙之挑战　目标一览","image_path":"https://dragalialost.akamaized.net/attached/information/images/470077a7e774513d2ee4503ee7c91d45.png","date":1581746400,"is_new":false,"is_update":false,"update_time":1647325568}]},"category_id":"4","new_article_list":[],"update_article_list":[]}}