{"data_headers":{"result_code":1},"data":{"category":{"pr_category_id":"","more_posts":true,"priority_lower_than":"1716","contents":[{"article_id":1729,"priority":1721,"category_name":"公告","pr_category_id":"1","caption_type":"none","pr_thumb_type":null,"title_name":"“龙辉护符交换所”追加新的龙辉护符！","image_path":"","date":1603778400,"is_new":false,"is_update":false,"update_time":1603767376},{"article_id":1724,"priority":1720,"category_name":"公告","pr_category_id":"1","caption_type":"none","pr_thumb_type":null,"title_name":"部分任务周常奖励调整公告","image_path":"","date":1603681200,"is_new":false,"is_update":false,"update_time":1603681258},{"article_id":1722,"priority":1719,"category_name":"活动","pr_category_id":"4","caption_type":"none","pr_thumb_type":null,"title_name":"“星魂解放团队战”即将登场！","image_path":"https://dragalialost.akamaized.net/attached/information/images/6e322df872571aec3a4a3449c8c0ff7a.png","date":1603692000,"is_new":false,"is_update":false,"update_time":1603363659},{"article_id":20004,"priority":1718,"category_name":"活动","pr_category_id":"4","caption_type":"none","pr_thumb_type":null,"title_name":"“阿尔贝里亚大逃杀”活动日程【更新】","image_path":"","date":1603681200,"is_new":false,"is_update":false,"update_time":1640325972},{"article_id":1690,"priority":1717,"category_name":"公告","pr_category_id":"1","caption_type":"none","pr_thumb_type":null,"title_name":"“纳姆的波澜冒险记！”第10话更新","image_path":"","date":1603692000,"is_new":false,"is_update":false,"update_time":1602490190},{"article_id":1706,"priority":1716,"category_name":"活动","pr_category_id":"4","caption_type":"none","pr_thumb_type":null,"title_name":"“星魂解放团队战”登场！","image_path":"https://dragalialost.akamaized.net/attached/information/images/6e322df872571aec3a4a3449c8c0ff7a.png","date":1603519200,"is_new":false,"is_update":false,"update_time":1602817568}]},"category_id":"","new_article_list":[],"update_article_list":[]}}