{"data_headers":{"result_code":1},"data":{"category":{"pr_category_id":"","more_posts":true,"priority_lower_than":"492","contents":[{"article_id":495,"priority":499,"category_name":"公告","pr_category_id":"1","caption_type":"none","pr_thumb_type":null,"title_name":"“轻松龙约”第113话更新","image_path":"","date":1560319200,"is_new":false,"is_update":false,"update_time":1558944878},{"article_id":513,"priority":498,"category_name":"活动","pr_category_id":"4","caption_type":"event","pr_thumb_type":null,"title_name":"团队活动“仙境苍穹路”终章追加！","image_path":"","date":1560319200,"is_new":false,"is_update":false,"update_time":1559902225},{"article_id":512,"priority":495,"category_name":"活动","pr_category_id":"4","caption_type":"event","pr_thumb_type":null,"title_name":"“波塞冬·虚空之影”将在虚空之影讨伐战中登场！","image_path":"","date":1560232800,"is_new":false,"is_update":false,"update_time":1560232962},{"article_id":494,"priority":494,"category_name":"公告","pr_category_id":"1","caption_type":"none","pr_thumb_type":null,"title_name":"“轻松龙约”第112话更新","image_path":"","date":1560146400,"is_new":false,"is_update":false,"update_time":1558944471},{"article_id":501,"priority":493,"category_name":"公告","pr_category_id":"1","caption_type":"summon","pr_thumb_type":null,"title_name":"“龙传说召唤”开放！","image_path":"","date":1559973600,"is_new":false,"is_update":false,"update_time":1560224909},{"article_id":493,"priority":492,"category_name":"公告","pr_category_id":"1","caption_type":"none","pr_thumb_type":null,"title_name":"“轻松龙约”第111话更新","image_path":"","date":1559887200,"is_new":false,"is_update":false,"update_time":1558944262}]},"category_id":"","new_article_list":[],"update_article_list":[]}}