{"data_headers":{"result_code":1},"data":{"category":{"pr_category_id":"1","more_posts":true,"priority_lower_than":"105","contents":[{"article_id":73,"priority":112,"category_name":"公告","pr_category_id":"1","caption_type":"none","pr_thumb_type":null,"title_name":"关于在"心地善良的少女与被困的守护龙"中发生的异常现象【追记】","image_path":"","date":1540979100,"is_new":false,"is_update":false,"update_time":1542364179},{"article_id":72,"priority":111,"category_name":"公告","pr_category_id":"1","caption_type":"none","pr_thumb_type":null,"title_name":"关于特定操作下使用远程攻击及远程技能时出现的异常现象","image_path":"","date":1540970100,"is_new":false,"is_update":false,"update_time":1541399541},{"article_id":71,"priority":110,"category_name":"公告","pr_category_id":"1","caption_type":"none","pr_thumb_type":null,"title_name":"关于部分技能的攻击范围调整【追记】","image_path":"","date":1540966800,"is_new":false,"is_update":false,"update_time":1542364063},{"article_id":66,"priority":108,"category_name":"公告","pr_category_id":"1","caption_type":"none","pr_thumb_type":null,"title_name":"“轻松龙约”第24话更新","image_path":"","date":1540965600,"is_new":false,"is_update":false,"update_time":1541473555},{"article_id":70,"priority":106,"category_name":"公告","pr_category_id":"1","caption_type":"summon","pr_thumb_type":null,"title_name":"“召唤”变更的注意事项","image_path":"","date":1540954800,"is_new":false,"is_update":false,"update_time":1542363997},{"article_id":67,"priority":105,"category_name":"公告","pr_category_id":"1","caption_type":"none","pr_thumb_type":null,"title_name":"关于龙之庭院中的礼物可能均显示为"面包"的异常现象【追记】","image_path":"","date":1540895400,"is_new":false,"is_update":false,"update_time":1542363943}]},"category_id":"1","new_article_list":[],"update_article_list":[]}}