{"data_headers":{"result_code":1},"data":{"category":{"pr_category_id":"1","more_posts":true,"priority_lower_than":"1990","contents":[{"article_id":1983,"priority":1996,"category_name":"公告","pr_category_id":"1","caption_type":"none","pr_thumb_type":null,"title_name":"“情人节登录奖励”活动开始！","image_path":"https://dragalialost.akamaized.net/attached/information/images/0eeefc5848d6e73c19903555096ff209.png","date":1613109600,"is_new":false,"is_update":false,"update_time":1612839549},{"article_id":1961,"priority":1994,"category_name":"公告","pr_category_id":"1","caption_type":"none","pr_thumb_type":"1","title_name":"“PERSONA5 SCRAMBLE 失心之乱活动纪念！《Dragalia Lost ～失落的龙约～》官方推特账号 关注&转推活动”开始！【更新】","image_path":"","date":1612072800,"is_new":false,"is_update":false,"update_time":1613109612},{"article_id":1982,"priority":1993,"category_name":"公告","pr_category_id":"1","caption_type":"none","pr_thumb_type":null,"title_name":"“龙辉护符交换所”追加期间限定龙辉护符！","image_path":"","date":1613109600,"is_new":false,"is_update":false,"update_time":1612768828},{"article_id":1985,"priority":1992,"category_name":"公告","pr_category_id":"1","caption_type":"none","pr_thumb_type":null,"title_name":"“阿尔贝里亚大逃杀”龙变更！","image_path":"","date":1613109600,"is_new":false,"is_update":false,"update_time":1612936879},{"article_id":10058,"priority":1991,"category_name":"公告","pr_category_id":"1","caption_type":"none","pr_thumb_type":"1","title_name":"近期活动相关情报","image_path":"https://dragalialost.akamaized.net/attached/information/images/b52c16ab5bcc149d1b76eaeba1cf5d05.png","date":1613109600,"is_new":false,"is_update":false,"update_time":1612251058},{"article_id":1943,"priority":1990,"category_name":"公告","pr_category_id":"1","caption_type":"none","pr_thumb_type":null,"title_name":"“轻松龙约”第321话更新","image_path":"","date":1613109600,"is_new":false,"is_update":false,"update_time":1611544463}]},"category_id":"1","new_article_list":[],"update_article_list":[]}}