{"data_headers":{"result_code":1},"data":{"category":{"pr_category_id":"1","more_posts":true,"priority_lower_than":"2575","contents":[{"article_id":2521,"priority":2590,"category_name":"公告","pr_category_id":"1","caption_type":"none","pr_thumb_type":null,"title_name":"“轻松龙约”第403话更新","image_path":"","date":1635400800,"is_new":false,"is_update":false,"update_time":1632742153},{"article_id":2553,"priority":2589,"category_name":"公告","pr_category_id":"1","caption_type":"none","pr_thumb_type":null,"title_name":"追加部分龙可进行上限解锁的第5阶段！","image_path":"","date":1635314400,"is_new":false,"is_update":false,"update_time":1635133100},{"article_id":2520,"priority":2580,"category_name":"公告","pr_category_id":"1","caption_type":"none","pr_thumb_type":null,"title_name":"“轻松龙约”第402话更新","image_path":"","date":1634882400,"is_new":false,"is_update":false,"update_time":1632741872},{"article_id":2571,"priority":2579,"category_name":"公告","pr_category_id":"1","caption_type":"none","pr_thumb_type":null,"title_name":"关于Android 12环境下的游戏显示问题","image_path":"","date":1634713200,"is_new":false,"is_update":false,"update_time":1634782464},{"article_id":2551,"priority":2576,"category_name":"公告","pr_category_id":"1","caption_type":"summon","pr_thumb_type":"6","title_name":"“传说甄选召唤”开放！","image_path":"","date":1634536800,"is_new":false,"is_update":false,"update_time":1634029158},{"article_id":2549,"priority":2575,"category_name":"公告","pr_category_id":"1","caption_type":"summon","pr_thumb_type":"6","title_name":"“风属性传说召唤”开放！","image_path":"","date":1634536800,"is_new":false,"is_update":false,"update_time":1634028349}]},"category_id":"1","new_article_list":[],"update_article_list":[]}}