{"data_headers":{"result_code":1},"data":{"category":{"pr_category_id":"5","more_posts":true,"priority_lower_than":"423","contents":[{"article_id":1344,"priority":1332,"category_name":"重要","pr_category_id":"5","caption_type":"none","pr_thumb_type":null,"title_name":"遊戲支援裝置相關重要公告","image_path":"","date":1590472800,"is_new":false,"is_update":false,"update_time":1590463957},{"article_id":1064,"priority":1070,"category_name":"重要","pr_category_id":"5","caption_type":"none","pr_thumb_type":null,"title_name":"關於不正當行為之停權處置公告","image_path":"","date":1581314400,"is_new":false,"is_update":false,"update_time":1580979704},{"article_id":781,"priority":778,"category_name":"重要","pr_category_id":"5","caption_type":"none","pr_thumb_type":null,"title_name":"商店功能維護公告【更新】","image_path":"","date":1569987900,"is_new":false,"is_update":false,"update_time":1570012297},{"article_id":780,"priority":777,"category_name":"重要","pr_category_id":"5","caption_type":"none","pr_thumb_type":null,"title_name":"配合日本消費稅稅率調整之商店價格變更公告【更新】","image_path":"","date":1569980700,"is_new":false,"is_update":false,"update_time":1570012160},{"article_id":526,"priority":522,"category_name":"重要","pr_category_id":"5","caption_type":"none","pr_thumb_type":null,"title_name":"【重要】遊戲資料備份相關公告","image_path":"","date":1561096800,"is_new":false,"is_update":false,"update_time":1561000110},{"article_id":426,"priority":423,"category_name":"重要","pr_category_id":"5","caption_type":"none","pr_thumb_type":null,"title_name":"進行召喚所需的「龍光鑽石」和「龍輝晶石」數量變更公告【更新】","image_path":"","date":1556263800,"is_new":false,"is_update":false,"update_time":1556264716}]},"category_id":"5","new_article_list":[],"update_article_list":[]}}