{"data_headers":{"result_code":1},"data":{"category":{"pr_category_id":"1","more_posts":true,"priority_lower_than":"2651","contents":[{"article_id":2647,"priority":2662,"category_name":"公告","pr_category_id":"1","caption_type":"none","pr_thumb_type":null,"title_name":"無法進行團隊遊戲之異常現象公告【更新】","image_path":"","date":1637981700,"is_new":false,"is_update":false,"update_time":1638239969},{"article_id":2646,"priority":2660,"category_name":"公告","pr_category_id":"1","caption_type":"none","pr_thumb_type":null,"title_name":"「同盟聊天頻道」中僅會顯示一定數量訊息之異常現象公告","image_path":"","date":1637917200,"is_new":false,"is_update":false,"update_time":1638239734},{"article_id":2633,"priority":2657,"category_name":"公告","pr_category_id":"1","caption_type":"none","pr_thumb_type":null,"title_name":"部分龍族追加第5階段上限解放！","image_path":"","date":1637820000,"is_new":false,"is_update":false,"update_time":1637550189},{"article_id":2641,"priority":2655,"category_name":"公告","pr_category_id":"1","caption_type":"none","pr_thumb_type":null,"title_name":"「莉莉斯封滅戰　絕級」掉落獎勵之異常現象公告【更新】","image_path":"","date":1637745300,"is_new":false,"is_update":false,"update_time":1637913534},{"article_id":2582,"priority":2653,"category_name":"公告","pr_category_id":"1","caption_type":"none","pr_thumb_type":null,"title_name":"「輕鬆龍絆」第410話更新","image_path":"","date":1637733600,"is_new":false,"is_update":false,"update_time":1634882296},{"article_id":2619,"priority":2651,"category_name":"公告","pr_category_id":"1","caption_type":"none","pr_thumb_type":null,"title_name":"主線劇情第22章「兩位契約者」後半登場！","image_path":"https://dragalialost.akamaized.net/attached/information/images/6580be312722ee30fafff32eb0763d90.png","date":1637560800,"is_new":false,"is_update":false,"update_time":1637545060}]},"category_id":"1","new_article_list":[],"update_article_list":[]}}