{"data_headers":{"result_code":1},"data":{"category":{"pr_category_id":"1","more_posts":true,"priority_lower_than":"2736","contents":[{"article_id":2706,"priority":2744,"category_name":"公告","pr_category_id":"1","caption_type":"none","pr_thumb_type":null,"title_name":"「新春福袋」販售公告","image_path":"https://dragalialost.akamaized.net/attached/information/images/ef175454ba3ab364da8eb636178bf936.png","date":1640325600,"is_new":false,"is_update":false,"update_time":1640068260},{"article_id":2719,"priority":2743,"category_name":"公告","pr_category_id":"1","caption_type":"summon","pr_thumb_type":"6","title_name":"「失落龍絆日」舉辦公告","image_path":"","date":1640844000,"is_new":false,"is_update":false,"update_time":1640689289},{"article_id":2741,"priority":2741,"category_name":"公告","pr_category_id":"1","caption_type":"none","pr_thumb_type":null,"title_name":"「萬花筒迷宮」中發生錯誤而無法繼續關卡之異常現象公告","image_path":"","date":1640686800,"is_new":false,"is_update":false,"update_time":1641354050},{"article_id":2740,"priority":2740,"category_name":"公告","pr_category_id":"1","caption_type":"none","pr_thumb_type":null,"title_name":"Android裝置發生進行任務途中畫面靜止不動之異常現象公告","image_path":"","date":1640683800,"is_new":false,"is_update":false,"update_time":1640682955},{"article_id":2722,"priority":2737,"category_name":"公告","pr_category_id":"1","caption_type":"none","pr_thumb_type":null,"title_name":"元旦連續假期期間客服服務公告","image_path":"","date":1640671200,"is_new":false,"is_update":false,"update_time":1640250619},{"article_id":2656,"priority":2736,"category_name":"公告","pr_category_id":"1","caption_type":"none","pr_thumb_type":null,"title_name":"「輕鬆龍絆」第419話更新","image_path":"","date":1640671200,"is_new":false,"is_update":false,"update_time":1638239820}]},"category_id":"1","new_article_list":[],"update_article_list":[]}}