{"data_headers":{"result_code":1},"data":{"category":{"pr_category_id":"1","more_posts":true,"priority_lower_than":"2820","contents":[{"article_id":2805,"priority":2826,"category_name":"公告","pr_category_id":"1","caption_type":"none","pr_thumb_type":null,"title_name":"「輕鬆龍絆」第428話更新","image_path":"","date":1643781600,"is_new":false,"is_update":false,"update_time":1643332368},{"article_id":2817,"priority":2825,"category_name":"公告","pr_category_id":"1","caption_type":"none","pr_thumb_type":"4","title_name":"本月的「Dragalia Lost ～失落的龍絆～」","image_path":"","date":1643695200,"is_new":false,"is_update":false,"update_time":1643592830},{"article_id":2801,"priority":2824,"category_name":"公告","pr_category_id":"1","caption_type":"none","pr_thumb_type":null,"title_name":"商店內的道具購買次數和交換次數更新公告","image_path":"","date":1643695200,"is_new":false,"is_update":false,"update_time":1643246667},{"article_id":2795,"priority":2823,"category_name":"公告","pr_category_id":"1","caption_type":"summon","pr_thumb_type":"6","title_name":"「失落龍絆日」開始舉辦！","image_path":"","date":1643608800,"is_new":false,"is_update":false,"update_time":1643766039},{"article_id":2792,"priority":2821,"category_name":"公告","pr_category_id":"1","caption_type":"none","pr_thumb_type":null,"title_name":"「Lord of the Blood 登入獎勵」開始舉辦！","image_path":"https://dragalialost.akamaized.net/attached/information/images/bc9d64698213e74bc0686851300eb861.png","date":1643608800,"is_new":false,"is_update":false,"update_time":1643015102},{"article_id":2816,"priority":2820,"category_name":"公告","pr_category_id":"1","caption_type":"none","pr_thumb_type":null,"title_name":"「龍輝護符交換所」追加新龍輝護符公告","image_path":"","date":1643608800,"is_new":false,"is_update":false,"update_time":1643592327}]},"category_id":"1","new_article_list":[],"update_article_list":[]}}